setup.py
dl_rank/__init__.py
dl_rank/solo.py
dl_rank/symphony.py
dl_rank.egg-info/PKG-INFO
dl_rank.egg-info/SOURCES.txt
dl_rank.egg-info/dependency_links.txt
dl_rank.egg-info/not-zip-safe
dl_rank.egg-info/requires.txt
dl_rank.egg-info/top_level.txt
dl_rank/conf/BaseParser.py
dl_rank/conf/__init__.py
dl_rank/file/__init__.py
dl_rank/file/fileUtils.py
dl_rank/file/file_api.py
dl_rank/file/wfile.py
dl_rank/layer/__init__.py
dl_rank/layer/best_checkpoint_copier.py
dl_rank/layer/layers.py
dl_rank/model/BaseModel.py
dl_rank/model/ModelFactory.py
dl_rank/model/__init__.py
dl_rank/model/dcn.py
dl_rank/model/deepfm.py
dl_rank/model/deepfm_pair.py
dl_rank/model/deepfm_v2.py
dl_rank/model/wide_and_deep.py
dl_rank/model/wide_deep_traditional_attention.py
dl_rank/model/xcross.py
dl_rank/model/xdeepfm.py
dl_rank/tensorflowonspark/TFCluster.py
dl_rank/tensorflowonspark/TFManager.py
dl_rank/tensorflowonspark/TFNode.py
dl_rank/tensorflowonspark/TFSparkNode.py
dl_rank/tensorflowonspark/__init__.py
dl_rank/tensorflowonspark/dfutil.py
dl_rank/tensorflowonspark/gpu_info.py
dl_rank/tensorflowonspark/marker.py
dl_rank/tensorflowonspark/pipeline.py
dl_rank/tensorflowonspark/reservation.py
dl_rank/tensorflowonspark/reservation_client.py
dl_rank/tensorflowonspark/util.py
dl_rank/utils/__init__.py
dl_rank/utils/configManager.py
dl_rank/utils/csvResult2json.py
dl_rank/utils/dataHelper.py
dl_rank/utils/item_profile_parse.py
dl_rank/utils/modelUtils.py
dl_rank/utils/preprocess.py
dl_rank/utils/scriptHelper.py
dl_rank/utils/yamlHelper.py